ambient_edge_server/__init__.py
ambient_edge_server/app.py
ambient_edge_server/builtin_plugins.yml
ambient_edge_server/config.py
ambient_edge_server/run.py
ambient_edge_server/assets/word_art.txt
ambient_edge_server/event_handlers/__init__.py
ambient_edge_server/event_handlers/authorize_to_registry_handler.py
ambient_edge_server/event_handlers/base_handler.py
ambient_edge_server/event_handlers/deploy_service_handler.py
ambient_edge_server/models/__init__.py
ambient_edge_server/models/api.py
ambient_edge_server/models/sql_models.py
ambient_edge_server/models/system_service.py
ambient_edge_server/repos/__init__.py
ambient_edge_server/repos/device_auth_repo.py
ambient_edge_server/repos/node_repo.py
ambient_edge_server/repos/plugin_repo.py
ambient_edge_server/repos/sql_base_repo.py
ambient_edge_server/repos/system_daemon_repo.py
ambient_edge_server/repos/token_repo.py
ambient_edge_server/routers/__init__.py
ambient_edge_server/routers/auth.py
ambient_edge_server/routers/crud.py
ambient_edge_server/routers/daemon.py
ambient_edge_server/routers/health.py
ambient_edge_server/routers/ping.py
ambient_edge_server/routers/plugins.py
ambient_edge_server/routers/ports.py
ambient_edge_server/routers/software.py
ambient_edge_server/services/__init__.py
ambient_edge_server/services/authorization_service.py
ambient_edge_server/services/crud_service.py
ambient_edge_server/services/docker_service.py
ambient_edge_server/services/event_service.py
ambient_edge_server/services/health_service.py
ambient_edge_server/services/interface_service.py
ambient_edge_server/services/port_service.py
ambient_edge_server/services/registry_service.py
ambient_edge_server/services/service_manager.py
ambient_edge_server/services/system_daemon_service.py
ambient_edge_server/services/upgrade_service.py
ambient_edge_server/templates/ambient_edge_server.service.jinja2
ambient_edge_server/utils/__init__.py
ambient_edge_server-1.8.0.dist-info/METADATA
ambient_edge_server-1.8.0.dist-info/WHEEL
ambient_edge_server-1.8.0.dist-info/entry_points.txt
ambient_edge_server-1.8.0.dist-info/top_level.txt
ambient_edge_server-1.8.0.dist-info/RECORD
