Metadata-Version: 2.1
Name: ambient-edge-server
Version: 1.8.0
Summary: Ambient Edge Server
Author: Ambient Labs Computing - An Edge Compute Company
Author-email: jose@ambientlabscomputing.com
Requires-Dist: ambient-event-bus-client==1.1.2
Requires-Dist: ambient-backend-api-client>=3.0.1
Requires-Dist: ambient-client-common==1.8.0
Requires-Dist: ambient-base-plugin==1.8.0
Requires-Dist: ambient-docker-swarm-plugin==1.8.0
Requires-Dist: ambient-run-command-plugin==1.8.0
Requires-Dist: fastapi==0.111.0
Requires-Dist: pydantic==2.7.4
Requires-Dist: setuptools==69.5.1
Requires-Dist: pydantic-settings==2.3.1
Requires-Dist: aiohttp==3.9.5
Requires-Dist: cryptography==42.0.8
Requires-Dist: async-lru==2.0.4
Requires-Dist: result>=0.17.0
Requires-Dist: websockets==12.0
Requires-Dist: docker==7.1.0
Requires-Dist: jinja2==3.1.4
Requires-Dist: psutil==5.9.8
Requires-Dist: loguru==0.7.2
Requires-Dist: SQLAlchemy==2.0.40
Requires-Dist: alembic==1.15.2
Requires-Dist: aiosqlite==0.21.0
Requires-Dist: pydantic-extra-types==2.10.4
